cma_atlas/__init__.py
cma_atlas/__main__.py
cma_atlas/abcs.py
cma_atlas/cli.py
cma_atlas/core.py
cma_atlas/errors.py
cma_atlas/interfaces.py
cma_atlas/test_interfaces.py
cma_atlas/resources/default_options.yml
cma_atlas/utils/constants.py
cma_atlas/utils/strings.py
cma_atlas/utils/tools.py
cma_atlas-0.1.0a3.dist-info/LICENSE
cma_atlas-0.1.0a3.dist-info/METADATA
cma_atlas-0.1.0a3.dist-info/WHEEL
cma_atlas-0.1.0a3.dist-info/entry_points.txt
cma_atlas-0.1.0a3.dist-info/top_level.txt
cma_atlas-0.1.0a3.dist-info/RECORD
