Metadata-Version: 2.1
Name: cma-atlas
Version: 0.1.0a3
Summary: A dynamic interface with many remote databases of biological data
Home-page: https://github.com/CMA-Lab/Atlas
Author: MrHedmad
Author-email: luca.visentin@unito.it
Project-URL: Bug Tracker, https://github.com/CMA-Lab/Atlas/issues
Classifier: Programming Language :: Python :: 3
Classifier: License :: OSI Approved :: MIT License
Classifier: Operating System :: POSIX :: Linux
Requires-Python: >=3.10
License-File: LICENSE
Requires-Dist: typer
Requires-Dist: colorama
Requires-Dist: pyyaml
Requires-Dist: tqdm
Requires-Dist: pandas
Requires-Dist: requests
Requires-Dist: simple-term-menu
